journel/__init__.py
journel/cli.py
journel/config.py
journel/display.py
journel/help_text.py
journel/models.py
journel/session.py
journel/storage.py
journel/tui.py
journel/utils.py
journel-0.1.0.dist-info/LICENSE
journel-0.1.0.dist-info/METADATA
journel-0.1.0.dist-info/WHEEL
journel-0.1.0.dist-info/entry_points.txt
journel-0.1.0.dist-info/top_level.txt
journel-0.1.0.dist-info/RECORD
